JavaNioJianmingJiaocheng/README.md
JavaNioJianmingJiaocheng/__init__.py
JavaNioJianmingJiaocheng/__main__.py
JavaNioJianmingJiaocheng/file.epub
JavaNioJianmingJiaocheng/index.html
JavaNioJianmingJiaocheng/css/__init__.py
JavaNioJianmingJiaocheng/css/annotations.css
JavaNioJianmingJiaocheng/css/main.css
JavaNioJianmingJiaocheng/css/normalize.css
JavaNioJianmingJiaocheng/css/popup.css
JavaNioJianmingJiaocheng/font/__init__.py
JavaNioJianmingJiaocheng/font/fontello.eot
JavaNioJianmingJiaocheng/font/fontello.svg
JavaNioJianmingJiaocheng/font/fontello.ttf
JavaNioJianmingJiaocheng/font/fontello.woff
JavaNioJianmingJiaocheng/img/__init__.py
JavaNioJianmingJiaocheng/img/annotator-glyph-sprite.png
JavaNioJianmingJiaocheng/img/annotator-icon-sprite.png
JavaNioJianmingJiaocheng/img/apple-touch-icon.png
JavaNioJianmingJiaocheng/img/cancelfullscreen.png
JavaNioJianmingJiaocheng/img/close.png
JavaNioJianmingJiaocheng/img/fullscreen.png
JavaNioJianmingJiaocheng/img/loader.gif
JavaNioJianmingJiaocheng/img/menu-icon.png
JavaNioJianmingJiaocheng/img/save.png
JavaNioJianmingJiaocheng/img/saved.png
JavaNioJianmingJiaocheng/img/settings-s.png
JavaNioJianmingJiaocheng/img/settings.png
JavaNioJianmingJiaocheng/img/star.png
JavaNioJianmingJiaocheng/js/__init__.py
JavaNioJianmingJiaocheng/js/epub.js
JavaNioJianmingJiaocheng/js/epub.min.js
JavaNioJianmingJiaocheng/js/epub.min.map
JavaNioJianmingJiaocheng/js/hooks.min.js
JavaNioJianmingJiaocheng/js/hooks.min.map
JavaNioJianmingJiaocheng/js/reader.js
JavaNioJianmingJiaocheng/js/reader.js.map
JavaNioJianmingJiaocheng/js/reader.min.js
JavaNioJianmingJiaocheng/js/reader.min.map
JavaNioJianmingJiaocheng/js/hooks/__init__.py
JavaNioJianmingJiaocheng/js/hooks/extensions/__init__.py
JavaNioJianmingJiaocheng/js/hooks/extensions/highlight.js
JavaNioJianmingJiaocheng/js/libs/__init__.py
JavaNioJianmingJiaocheng/js/libs/jquery.min.js
JavaNioJianmingJiaocheng/js/libs/localforage.min.js
JavaNioJianmingJiaocheng/js/libs/screenfull.js
java_nio_jianming_jiaocheng-2024.3.3.0.dist-info/METADATA
java_nio_jianming_jiaocheng-2024.3.3.0.dist-info/WHEEL
java_nio_jianming_jiaocheng-2024.3.3.0.dist-info/entry_points.txt
java_nio_jianming_jiaocheng-2024.3.3.0.dist-info/top_level.txt
java_nio_jianming_jiaocheng-2024.3.3.0.dist-info/RECORD
